[
    {
        "firstPlayerId": "ngocnguyen",
        "secondPlayerId": "phongnguyen",
        "games": [
            {
                "result": 2
            },
            {
                "result": 0
            }
        ],
        "date": "2024-07-01"
    },
    {
        "firstPlayerId": "haicao",
        "secondPlayerId": "thangle",
        "games": [
            {
                "result": 1
            },
            {
                "result": 2
            }
        ],
        "date": "2024-07-01"
    },
    {
        "firstPlayerId": "thinhdoan",
        "secondPlayerId": "quyettran",
        "games": [
            {
                "result": 1
            },
            {
                "result": 0
            }
        ],
        "date": "2024-07-03"
    },
    {
        "firstPlayerId": "tuanquach",
        "secondPlayerId": "chuyennguyen",
        "games": [
            {
                "result": 2
            },
            {
                "result": 2
            }
        ],
        "date": "2024-07-03"
    },
    {
        "firstPlayerId": "tuanquach",
        "secondPlayerId": "thinhdoan",
        "games": [
            {
                "result": 0
            },
            {
                "result": 2
            }
        ],
        "date": "2024-07-05"
    },
    {
        "firstPlayerId": "quanvu",
        "secondPlayerId": "tungnguyen",
        "games": [
            {
                "result": 0
            },
            {
                "result": 2
            }
        ],
        "date": "2024-07-07"
    },
    {
        "firstPlayerId": "phongnguyen",
        "secondPlayerId": "thanhtran",
        "games": [
            {
                "result": 0
            },
            {
                "result": 2
            }
        ],
        "date": "2024-07-08"
    },
    {
        "firstPlayerId": "tungdai",
        "secondPlayerId": "thanhtran",
        "games": [
            {
                "result": 2
            },
            {
                "result": 0
            }
        ],
        "date": "2024-07-09"
    },
    {
        "firstPlayerId": "tungdai",
        "secondPlayerId": "chuyennguyen",
        "games": [
            {
                "result": 0
            },
            {
                "result": 1
            }
        ],
        "date": "2024-07-09"
    },
    {
        "firstPlayerId": "haicao",
        "secondPlayerId": "tungnguyen",
        "games": [],
        "date": "2024-07-10"
    },
    {
        "firstPlayerId": "ngocnguyen",
        "secondPlayerId": "thangle",
        "games": [],
        "date": "2024-07-11"
    },
    {
        "firstPlayerId": "quanvu",
        "secondPlayerId": "quyettran",
        "games": [],
        "date": "2024-07-12"
    }
]
